{
  "kind": "Program",
  "attributes": {
    "val": "null"
  },
  "children": [
    {
      "kind": "Imports",
      "attributes": {
        "val": "null"
      },
      "children": [
        {
          "kind": "ImportDeclaration",
          "attributes": {
            "val": "io.jgh.op.i",
            "col": "8",
            "line": "1"
          },
          "children": []
        },
        {
          "kind": "ImportDeclaration",
          "attributes": {
            "val": "a",
            "col": "8",
            "line": "2"
          },
          "children": []
        },
        {
          "kind": "ImportDeclaration",
          "attributes": {
            "val": "a.Fac1.b",
            "col": "8",
            "line": "3"
          },
          "children": []
        }
      ]
    },
    {
      "kind": "Class",
      "attributes": {
        "val": "Fac B",
        "col": "7",
        "line": "4"
      },
      "children": [
        {
          "kind": "MethodDeclaration",
          "attributes": {
            "val": "null"
          },
          "children": [
            {
              "kind": "RegularMethod",
              "attributes": {
                "val": "ComputeFac1",
                "col": "16",
                "line": "5"
              },
              "children": [
                {
                  "kind": "ReturnType",
                  "attributes": {
                    "val": "null"
                  },
                  "children": [
                    {
                      "kind": "Type",
                      "attributes": {
                        "val": "int",
                        "col": "12",
                        "line": "5"
                      },
                      "children": []
                    }
                  ]
                },
                {
                  "kind": "MethodParams",
                  "attributes": {
                    "val": "null"
                  },
                  "children": [
                    {
                      "kind": "MethodParam",
                      "attributes": {
                        "val": "null"
                      },
                      "children": [
                        {
                          "kind": "Type",
                          "attributes": {
                            "val": "int",
                            "col": "27",
                            "line": "5"
                          },
                          "children": []
                        },
                        {
                          "kind": "VarId",
                          "attributes": {
                            "val": "num",
                            "col": "31",
                            "line": "5"
                          },
                          "children": []
                        }
                      ]
                    },
                    {
                      "kind": "MethodParam",
                      "attributes": {
                        "val": "null"
                      },
                      "children": [
                        {
                          "kind": "Type",
                          "attributes": {
                            "val": "boolean",
                            "col": "36",
                            "line": "5"
                          },
                          "children": []
                        },
                        {
                          "kind": "VarId",
                          "attributes": {
                            "val": "a",
                            "col": "44",
                            "line": "5"
                          },
                          "children": []
                        }
                      ]
                    },
                    {
                      "kind": "MethodParam",
                      "attributes": {
                        "val": "null"
                      },
                      "children": [
                        {
                          "kind": "Type",
                          "attributes": {
                            "val": "int[]",
                            "col": "47",
                            "line": "5"
                          },
                          "children": []
                        },
                        {
                          "kind": "VarId",
                          "attributes": {
                            "val": "c34d",
                            "col": "53",
                            "line": "5"
                          },
                          "children": []
                        }
                      ]
                    }
                  ]
                },
                {
                  "kind": "MethodBody",
                  "attributes": {
                    "val": "null"
                  },
                  "children": [
                    {
                      "kind": "VarDeclaration",
                      "attributes": {
                        "val": "null"
                      },
                      "children": [
                        {
                          "kind": "Type",
                          "attributes": {
                            "val": "int",
                            "col": "9",
                            "line": "6"
                          },
                          "children": []
                        },
                        {
                          "kind": "VarId",
                          "attributes": {
                            "val": "num_aux",
                            "col": "13",
                            "line": "6"
                          },
                          "children": []
                        }
                      ]
                    },
                    {
                      "kind": "VarDeclaration",
                      "attributes": {
                        "val": "null"
                      },
                      "children": [
                        {
                          "kind": "Type",
                          "attributes": {
                            "val": "ab",
                            "col": "9",
                            "line": "7"
                          },
                          "children": []
                        },
                        {
                          "kind": "VarId",
                          "attributes": {
                            "val": "a",
                            "col": "12",
                            "line": "7"
                          },
                          "children": []
                        }
                      ]
                    },
                    {
                      "kind": "While",
                      "attributes": {
                        "val": "null"
                      },
                      "children": [
                        {
                          "kind": "WhileBody",
                          "attributes": {
                            "val": "null"
                          },
                          "children": [
                            {
                              "kind": "Scope",
                              "attributes": {
                                "val": "null"
                              },
                              "children": [
                                {
                                  "kind": "Var",
                                  "attributes": {
                                    "val": "a",
                                    "col": "13",
                                    "line": "9"
                                  },
                                  "children": []
                                },
                                {
                                  "kind": "Assignment",
                                  "attributes": {
                                    "val": "null",
                                    "col": "14",
                                    "line": "9"
                                  },
                                  "children": [
                                    {
                                      "kind": "IntegerLiteral",
                                      "attributes": {
                                        "val": "1",
                                        "col": "15",
                                        "line": "9"
                                      },
                                      "children": []
                                    }
                                  ]
                                }
                              ]
                            }
                          ]
                        }
                      ]
                    },
                    {
                      "kind": "While",
                      "attributes": {
                        "val": "null"
                      },
                      "children": [
                        {
                          "kind": "WhileExpression",
                          "attributes": {
                            "val": "null",
                            "col": "14",
                            "line": "11"
                          },
                          "children": [
                            {
                              "kind": "Var",
                              "attributes": {
                                "val": "a",
                                "col": "15",
                                "line": "11"
                              },
                              "children": []
                            },
                            {
                              "kind": "Less",
                              "attributes": {
                                "val": "null"
                              },
                              "children": [
                                {
                                  "kind": "IntegerLiteral",
                                  "attributes": {
                                    "val": "1",
                                    "col": "19",
                                    "line": "11"
                                  },
                                  "children": []
                                }
                              ]
                            }
                          ]
                        },
                        {
                          "kind": "WhileBody",
                          "attributes": {
                            "val": "null"
                          },
                          "children": [
                            {
                              "kind": "Scope",
                              "attributes": {
                                "val": "null"
                              },
                              "children": [
                                {
                                  "kind": "Var",
                                  "attributes": {
                                    "val": "a",
                                    "col": "13",
                                    "line": "12"
                                  },
                                  "children": []
                                },
                                {
                                  "kind": "Assignment",
                                  "attributes": {
                                    "val": "null",
                                    "col": "15",
                                    "line": "12"
                                  },
                                  "children": [
                                    {
                                      "kind": "Var",
                                      "attributes": {
                                        "val": "a",
                                        "col": "17",
                                        "line": "12"
                                      },
                                      "children": []
                                    },
                                    {
                                      "kind": "PlusExpression",
                                      "attributes": {
                                        "val": "null"
                                      },
                                      "children": [
                                        {
                                          "kind": "IntegerLiteral",
                                          "attributes": {
                                            "val": "1",
                                            "col": "21",
                                            "line": "12"
                                          },
                                          "children": []
                                        }
                                      ]
                                    }
                                  ]
                                }
                              ]
                            }
                          ]
                        }
                      ]
                    },
                    {
                      "kind": "IfAndElse",
                      "attributes": {
                        "val": "null"
                      },
                      "children": [
                        {
                          "kind": "IfExpression",
                          "attributes": {
                            "val": "null",
                            "col": "12",
                            "line": "44"
                          },
                          "children": [
                            {
                              "kind": "Var",
                              "attributes": {
                                "val": "num",
                                "col": "13",
                                "line": "44"
                              },
                              "children": []
                            },
                            {
                              "kind": "Less",
                              "attributes": {
                                "val": "null"
                              },
                              "children": [
                                {
                                  "kind": "IntegerLiteral",
                                  "attributes": {
                                    "val": "1",
                                    "col": "19",
                                    "line": "44"
                                  },
                                  "children": []
                                }
                              ]
                            }
                          ]
                        },
                        {
                          "kind": "IfBody",
                          "attributes": {
                            "val": "null"
                          },
                          "children": [
                            {
                              "kind": "Var",
                              "attributes": {
                                "val": "num_aux",
                                "col": "13",
                                "line": "45"
                              },
                              "children": []
                            },
                            {
                              "kind": "Assignment",
                              "attributes": {
                                "val": "null",
                                "col": "21",
                                "line": "45"
                              },
                              "children": [
                                {
                                  "kind": "IntegerLiteral",
                                  "attributes": {
                                    "val": "1",
                                    "col": "23",
                                    "line": "45"
                                  },
                                  "children": []
                                }
                              ]
                            }
                          ]
                        },
                        {
                          "kind": "ElseBody",
                          "attributes": {
                            "val": "null"
                          },
                          "children": [
                            {
                              "kind": "Var",
                              "attributes": {
                                "val": "num_aux",
                                "col": "13",
                                "line": "47"
                              },
                              "children": []
                            },
                            {
                              "kind": "Assignment",
                              "attributes": {
                                "val": "null",
                                "col": "21",
                                "line": "47"
                              },
                              "children": [
                                {
                                  "kind": "SubExpression",
                                  "attributes": {
                                    "val": "null"
                                  },
                                  "children": [
                                    {
                                      "kind": "IntegerLiteral",
                                      "attributes": {
                                        "val": "1",
                                        "col": "24",
                                        "line": "47"
                                      },
                                      "children": []
                                    },
                                    {
                                      "kind": "PlusExpression",
                                      "attributes": {
                                        "val": "null"
                                      },
                                      "children": [
                                        {
                                          "kind": "IntegerLiteral",
                                          "attributes": {
                                            "val": "2",
                                            "col": "28",
                                            "line": "47"
                                          },
                                          "children": []
                                        },
                                        {
                                          "kind": "MultExpression",
                                          "attributes": {
                                            "val": "null"
                                          },
                                          "children": [
                                            {
                                              "kind": "IntegerLiteral",
                                              "attributes": {
                                                "val": "2",
                                                "col": "32",
                                                "line": "47"
                                              },
                                              "children": []
                                            }
                                          ]
                                        }
                                      ]
                                    }
                                  ]
                                },
                                {
                                  "kind": "MultExpression",
                                  "attributes": {
                                    "val": "null"
                                  },
                                  "children": [
                                    {
                                      "kind": "IntegerLiteral",
                                      "attributes": {
                                        "val": "5",
                                        "col": "37",
                                        "line": "47"
                                      },
                                      "children": []
                                    }
                                  ]
                                }
                              ]
                            }
                          ]
                        }
                      ]
                    }
                  ]
                },
                {
                  "kind": "ReturnStatement",
                  "attributes": {
                    "val": "null"
                  },
                  "children": [
                    {
                      "kind": "Var",
                      "attributes": {
                        "val": "num_aux",
                        "col": "16",
                        "line": "52"
                      },
                      "children": []
                    }
                  ]
                }
              ]
            }
          ]
        },
        {
          "kind": "MethodDeclaration",
          "attributes": {
            "val": "null"
          },
          "children": [
            {
              "kind": "RegularMethod",
              "attributes": {
                "val": "b1",
                "col": "16",
                "line": "55"
              },
              "children": [
                {
                  "kind": "ReturnType",
                  "attributes": {
                    "val": "null"
                  },
                  "children": [
                    {
                      "kind": "Type",
                      "attributes": {
                        "val": "int",
                        "col": "12",
                        "line": "55"
                      },
                      "children": []
                    }
                  ]
                },
                {
                  "kind": "MethodBody",
                  "attributes": {
                    "val": "null"
                  },
                  "children": []
                },
                {
                  "kind": "ReturnStatement",
                  "attributes": {
                    "val": "null"
                  },
                  "children": [
                    {
                      "kind": "IntegerLiteral",
                      "attributes": {
                        "val": "1",
                        "col": "16",
                        "line": "56"
                      },
                      "children": []
                    }
                  ]
                }
              ]
            }
          ]
        },
        {
          "kind": "MethodDeclaration",
          "attributes": {
            "val": "null"
          },
          "children": [
            {
              "kind": "Main",
              "attributes": {
                "val": "null"
              },
              "children": [
                {
                  "kind": "ArgName",
                  "attributes": {
                    "val": "args",
                    "col": "38",
                    "line": "59"
                  },
                  "children": []
                },
                {
                  "kind": "MethodBody",
                  "attributes": {
                    "val": "null"
                  },
                  "children": [
                    {
                      "kind": "VarDeclaration",
                      "attributes": {
                        "val": "null"
                      },
                      "children": [
                        {
                          "kind": "Type",
                          "attributes": {
                            "val": "A",
                            "col": "9",
                            "line": "60"
                          },
                          "children": []
                        },
                        {
                          "kind": "VarId",
                          "attributes": {
                            "val": "b",
                            "col": "11",
                            "line": "60"
                          },
                          "children": []
                        }
                      ]
                    },
                    {
                      "kind": "Var",
                      "attributes": {
                        "val": "io",
                        "col": "9",
                        "line": "61"
                      },
                      "children": []
                    },
                    {
                      "kind": "MethodInvocation",
                      "attributes": {
                        "val": "println",
                        "col": "12",
                        "line": "61"
                      },
                      "children": [
                        {
                          "kind": "MethodArgs",
                          "attributes": {
                            "val": "null"
                          },
                          "children": [
                            {
                              "kind": "MethodArg",
                              "attributes": {
                                "val": "null"
                              },
                              "children": [
                                {
                                  "kind": "ConstructorClass",
                                  "attributes": {
                                    "val": "Fac",
                                    "col": "24",
                                    "line": "61"
                                  },
                                  "children": []
                                },
                                {
                                  "kind": "MethodInvocation",
                                  "attributes": {
                                    "val": "ComputeFac",
                                    "col": "30",
                                    "line": "61"
                                  },
                                  "children": [
                                    {
                                      "kind": "MethodArgs",
                                      "attributes": {
                                        "val": "null"
                                      },
                                      "children": [
                                        {
                                          "kind": "MethodArg",
                                          "attributes": {
                                            "val": "null"
                                          },
                                          "children": [
                                            {
                                              "kind": "IntegerLiteral",
                                              "attributes": {
                                                "val": "10",
                                                "col": "41",
                                                "line": "61"
                                              },
                                              "children": []
                                            }
                                          ]
                                        },
                                        {
                                          "kind": "MethodArg",
                                          "attributes": {
                                            "val": "null"
                                          },
                                          "children": [
                                            {
                                              "kind": "Var",
                                              "attributes": {
                                                "val": "b",
                                                "col": "45",
                                                "line": "61"
                                              },
                                              "children": []
                                            }
                                          ]
                                        },
                                        {
                                          "kind": "MethodArg",
                                          "attributes": {
                                            "val": "null"
                                          },
                                          "children": [
                                            {
                                              "kind": "Var",
                                              "attributes": {
                                                "val": "a",
                                                "col": "48",
                                                "line": "61"
                                              },
                                              "children": []
                                            },
                                            {
                                              "kind": "ArrayIndex",
                                              "attributes": {
                                                "val": "null",
                                                "col": "49",
                                                "line": "61"
                                              },
                                              "children": [
                                                {
                                                  "kind": "IntegerLiteral",
                                                  "attributes": {
                                                    "val": "4",
                                                    "col": "50",
                                                    "line": "61"
                                                  },
                                                  "children": []
                                                }
                                              ]
                                            },
                                            {
                                              "kind": "PlusExpression",
                                              "attributes": {
                                                "val": "null"
                                              },
                                              "children": [
                                                {
                                                  "kind": "IntegerLiteral",
                                                  "attributes": {
                                                    "val": "7",
                                                    "col": "55",
                                                    "line": "61"
                                                  },
                                                  "children": []
                                                }
                                              ]
                                            }
                                          ]
                                        }
                                      ]
                                    }
                                  ]
                                }
                              ]
                            }
                          ]
                        }
                      ]
                    },
                    {
                      "kind": "ConstructorClass",
                      "attributes": {
                        "val": "Fac1",
                        "col": "13",
                        "line": "62"
                      },
                      "children": []
                    },
                    {
                      "kind": "MethodInvocation",
                      "attributes": {
                        "val": "ab",
                        "col": "20",
                        "line": "62"
                      },
                      "children": [
                        {
                          "kind": "MethodArgs",
                          "attributes": {
                            "val": "null"
                          },
                          "children": [
                            {
                              "kind": "MethodArg",
                              "attributes": {
                                "val": "null"
                              },
                              "children": [
                                {
                                  "kind": "Var",
                                  "attributes": {
                                    "val": "b",
                                    "col": "23",
                                    "line": "62"
                                  },
                                  "children": []
                                }
                              ]
                            }
                          ]
                        }
                      ]
                    }
                  ]
                }
              ]
            }
          ]
        }
      ]
    }
  ]
}